LICENSE
MANIFEST.in
README.rst
requirements.txt
setup.py
cms/__init__.py
cms/__init__.pyc
cms/admin.py
cms/admin.pyc
cms/context_processors.py
cms/context_processors.pyc
cms/forms.py
cms/forms.pyc
cms/models.py
cms/models.pyc
cms/tasks.py
cms/tasks.pyc
cms/utils.py
cms/utils.pyc
cms/views.py
cms/management/__init__.py
cms/management/__init__.pyc
cms/management/commands/__init__.py
cms/management/commands/__init__.pyc
cms/management/commands/import_from_git.py
cms/management/commands/import_from_git.pyc
cms/management/commands/tests/__init__.py
cms/management/commands/tests/__init__.pyc
cms/management/commands/tests/test_import_from_git.py
cms/management/commands/tests/__pycache__/test_import_from_git.cpython-27-PYTEST.pyc
cms/migrations/0001_initial.py
cms/migrations/0002_delete_categories_field.py
cms/migrations/0003_auto__add_field_post_last_author__add_field_category_last_author.py
cms/migrations/0004_auto__add_field_post_language__add_field_post_source__add_field_catego.py
cms/migrations/0005_auto__add_field_post_featured_in_category.py
cms/migrations/0006_auto__add_field_post_featured.py
cms/migrations/0007_auto__del_unique_category_slug.py
cms/migrations/0008_auto__del_unique_post_slug.py
cms/migrations/0009_auto__add_field_category_featured_in_navbar.py
cms/migrations/0010_auto.py
cms/migrations/0011_auto__add_field_category_position.py
cms/migrations/0012_auto__add_field_category_site.py
cms/migrations/0013_auto__add_localisation__add_field_post_localisation__del_field_categor.py
cms/migrations/0014_move_languages_to_localisations.py
cms/migrations/0015_auto__del_field_category_language__del_field_post_language.py
cms/migrations/0016_auto__add_field_post_position.py
cms/migrations/0017_auto__add_contentrepository.py
cms/migrations/0017_auto__del_field_contentrepository_license__add_field_contentrepository.py
cms/migrations/0018_auto__del_field_contentrepository_existing_license__del_field_contentr.py
unicore_cms_django.egg-info/PKG-INFO
unicore_cms_django.egg-info/SOURCES.txt
unicore_cms_django.egg-info/dependency_links.txt
unicore_cms_django.egg-info/not-zip-safe
unicore_cms_django.egg-info/requires.txt
unicore_cms_django.egg-info/top_level.txt
